BanditAgents/__init__.py
BanditAgents/mocks/__init__.py
BanditAgents/mocks/builders/__init__.py
BanditAgents/mocks/builders/contexts_builders/__init__.py
BanditAgents/mocks/builders/contexts_builders/simulation_context_builder.py
BanditAgents/mocks/builders/solvers_builders/__init__.py
BanditAgents/mocks/builders/solvers_builders/base_solver_builder.py
BanditAgents/src/__init__.py
BanditAgents/src/agents/__init__.py
BanditAgents/src/agents/agent.py
BanditAgents/src/agents/base_agent.py
BanditAgents/src/agents/simulation_agent.py
BanditAgents/src/contexts/__init__.py
BanditAgents/src/contexts/context.py
BanditAgents/src/contexts/simulation_context.py
BanditAgents/src/contexts/deployable/__init__.py
BanditAgents/src/contexts/deployable/deployable_context.py
BanditAgents/src/contexts/deployable/empty_context.py
BanditAgents/src/contexts/deployable/sync_context.py
BanditAgents/src/domain/__init__.py
BanditAgents/src/domain/context_action_args.py
BanditAgents/src/domain/solver_args.py
BanditAgents/src/domain/hyperparameters/__init__.py
BanditAgents/src/exceptions/__init__.py
BanditAgents/src/exceptions/context_exceptions/__init__.py
BanditAgents/src/exceptions/context_exceptions/invalid_action_data_exception.py
BanditAgents/src/solvers/__init__.py
BanditAgents/src/solvers/epsilon_solver.py
BanditAgents/src/solvers/sampling_solver.py
BanditAgents/src/solvers/solver.py
BanditAgents/src/solvers/ucb_solver.py
BanditAgents/src/solvers/weight_solver.py
Exemples/__init__.py
Exemples/agents_exemples/__init__.py
Exemples/agents_exemples/basic_agent_exemple.py
Exemples/agents_exemples/empty_context_agent_exemple.py
Exemples/basic_exemples/__init__.py
Exemples/basic_exemples/epsilon_solver_example.py
Exemples/basic_exemples/sampling_solver_example.py
Exemples/basic_exemples/ucb_solver_example.py
Exemples/basic_exemples/weight_solver_example.py
Exemples/performance_exemples/__init__.py
Exemples/performance_exemples/basic_performance_comparison_exemple.py
Tests/__init__.py
bandit_agents-0.5.23.dist-info/LICENSE
bandit_agents-0.5.23.dist-info/METADATA
bandit_agents-0.5.23.dist-info/WHEEL
bandit_agents-0.5.23.dist-info/top_level.txt
bandit_agents-0.5.23.dist-info/RECORD
