Metadata-Version: 2.2
Name: bandit-agents
Version: 0.5.23
Summary: Library to solve k-armed bandit problems
Author-email: Vincent Martel <vincent.martel.11235@gmail.com>
Keywords: machine learning,ml,k-armed bandit,multi armed bandit,k-armed,armed,multi,machine,learning,reinforcement,reinforcement learning,applied,mathematics,solver,agent,ressources,optimization,martel,allocation,allocate,artificial intelligence,ai,algorithm,problem solving,bandit
Classifier: Development Status :: 3 - Alpha
Classifier: Intended Audience :: Developers
Classifier: Programming Language :: Python :: 3
Classifier: Programming Language :: Python :: 3.9
Classifier: Programming Language :: Python :: 3.10
Classifier: Programming Language :: Python :: 3.11
Classifier: Programming Language :: Python :: 3.12
License-File: LICENSE
Requires-Dist: numpy==2.1.3
Requires-Dist: scipy==1.14.1
Dynamic: description
Dynamic: description-content-type
